{
  "year": 2020,
  "seq": 42,
  "meta": {
    "date": "2020-03-05",
    "from": "maryvonne masseron-mandaba <maryvonnemm@hotmail.com>",
    "to": "\"y.mandaba@gmail.com\" <y.mandaba@gmail.com>",
    "subject": "Medicaments"
  },
  "proposals": [],
  "raw_excerpt": "🗕 Date : 2020-03-05\n👤 From : maryvonne masseron-mandaba <maryvonnemm@hotmail.com>\n📨 To   : \"y.mandaba@gmail.com\" <y.mandaba@gmail.com>\n🧕 Subject : Medicaments\n---\nDemain nous passons au stade 3\nEpidemie Covid-19\nen France\n\nPsychose\nLes gens vident les boutiques et pharmacies\nJe ne pourrai vous dpanner\nManquons de mdicaments\nLes molcules de base sont fabriques en Chine...\n\nMerci de prendre en rserve pour Tristan\n2 flacons aerius sirop\n2 spray ventoline\n1 spray flixotide\n1 flacon sirop Amoxicilline-Acide clavulanique\n\nJe n'cris plus sur WhatsApp car il le gre !\nMerci pour le petit machin\nMaman\n\n\nTlcharger Outlook pour Android"
}