{
  "year": 2020,
  "seq": 46,
  "meta": {
    "date": "2020-03-06",
    "from": "maryvonne masseron-mandaba <maryvonnemm@hotmail.com>",
    "to": "\"y.mandaba@gmail.com\" <y.mandaba@gmail.com>",
    "subject": "2020-03-Bulletin Infovac special Coronavirus (1).pdf"
  },
  "proposals": [],
  "raw_excerpt": "🗕 Date : 2020-03-06\n👤 From : maryvonne masseron-mandaba <maryvonnemm@hotmail.com>\n📨 To   : \"y.mandaba@gmail.com\" <y.mandaba@gmail.com>\n🧕 Subject : 2020-03-Bulletin Infovac special Coronavirus (1).pdf\n---\nC'est ce que tu dis exactement\n\nTlcharger Outlook pour Android"
}