{
  "year": 2024,
  "seq": 87,
  "meta": {
    "date": "2024-10-24",
    "from": "MYM MANDABA SCI <mymmandaba@gmail.com>",
    "to": "Yannick Mandaba <y.mandaba@gmail.com>",
    "subject": "Re:"
  },
  "proposals": [
    {
      "index": -87,
      "etiquette": "Paiements via Western Union",
      "category": "MIN",
      "duration": "LT",
      "source": "AI",
      "score": 1,
      "matched_from": [
        "ai_new"
      ]
    }
  ],
  "raw_excerpt": "🗕 Date : 2024-10-24\n👤 From : MYM MANDABA SCI <mymmandaba@gmail.com>\n📨 To   : Yannick Mandaba <y.mandaba@gmail.com>\n🧕 Subject : Re:\n---\nQue tu as choisi de vivre en Thaïlande.\nAs-tu été chercher ton WU du 19 octobre ?\nMerci du reçu\n\nLe jeu. 24 oct. 2024, 06:45, Yannick Mandaba  a écrit :\n\n> Quand on te demande pourquoi je ne suis pas là qu'est ce que tu répond ?\n>"
}