{
  "year": 2018,
  "seq": 56,
  "meta": {
    "date": "2018-06-26",
    "from": "maryvonne masseron-mandaba <maryvonnemm@hotmail.com>",
    "to": "\"y.mandaba@gmail.com\" <y.mandaba@gmail.com>, Marc MANDABA",
    "subject": "les films du bapteme de Léa/ photos suivront"
  },
  "proposals": [],
  "raw_excerpt": "🗕 Date : 2018-06-26\n👤 From : maryvonne masseron-mandaba <maryvonnemm@hotmail.com>\n📨 To   : \"y.mandaba@gmail.com\" <y.mandaba@gmail.com>, Marc MANDABA\n\t<marcmandaba@hotmail.com>\n🧕 Subject : les films du bapteme de Léa/ photos suivront\n---\nhttps://we.tl/1wxgVgLoMX"
}