{
  "year": 2018,
  "seq": 126,
  "meta": {
    "date": "2018-10-03",
    "from": "maryvonne masseron-mandaba <maryvonnemm@hotmail.com>",
    "to": "\"y.mandaba@gmail.com\" <y.mandaba@gmail.com>, Marc MANDABA",
    "subject": "signature de licitation Appt 7 Bd St Martin à Vitré"
  },
  "proposals": [],
  "raw_excerpt": "🗕 Date : 2018-10-03\n👤 From : maryvonne masseron-mandaba <maryvonnemm@hotmail.com>\n📨 To   : \"y.mandaba@gmail.com\" <y.mandaba@gmail.com>, Marc MANDABA\n\t<marcmandaba@hotmail.com>\n🧕 Subject : signature de licitation Appt 7 Bd St Martin à Vitré\n---\nbonjour,\nhier,  l'Etude de Matre Chaudet, a t signe la licitation pour l'appartement de tante Jeannette. Succession JB : Saint Martin, Bas-Pont, terres agricoles.\nJe n'ai pas encore scann le document sign, mais voici le projet, qui n'a t modifi en aucun point.\n\nJ'ai encore t tacle pour retard  rsoudre la succession, mais\n\n  *\nj'attendais mon retour de Thalande, avec affinement des projets de Yannick et Bee\n  *\nle Bas-pont n'est pas encore vendu car il faut expulser un locataire ( avant le 15 oct)\n\nJ'espre faire pour le mieux.\nVous aurez un petit pied--terre  Vitr.\nBonne journe\nmaman"
}